README.rst
setup.py
aiohttp_bam/__init__.py
aiohttp_bam.egg-info/PKG-INFO
aiohttp_bam.egg-info/SOURCES.txt
aiohttp_bam.egg-info/dependency_links.txt
aiohttp_bam.egg-info/top_level.txt