Metadata-Version: 1.1
Name: aiohttp-bam
Version: 0.0.1
Summary: aiohttp basic auth middleware.
Home-page: https://github.com/codeif/aiohttp-bam
Author: codeif
Author-email: me@codeif.com
License: MIT
Platform: UNKNOWN
Classifier: Programming Language :: Python :: 3
